stackdidact/__init__.py
stackdidact/cli.py
stackdidact/generator.py
stackdidact/question.py
stackdidact/settings.py
stackdidact-1.1.0.dist-info/DESCRIPTION.rst
stackdidact-1.1.0.dist-info/METADATA
stackdidact-1.1.0.dist-info/RECORD
stackdidact-1.1.0.dist-info/WHEEL
stackdidact-1.1.0.dist-info/entry_points.txt
stackdidact-1.1.0.dist-info/metadata.json
stackdidact-1.1.0.dist-info/top_level.txt
