Metadata-Version: 2.0
Name: stackdidact
Version: 1.1.0
Summary: Fresh Questions from Stack Exchange family for those who want to learn something new **often**.
Home-page: https://github.com/kshitij10496/stackdidact
Author: Kshitij Saraogi
Author-email: kshitijsaraogi@gmail.com
License: MIT
Download-URL: https://github.com/kshitij10496/stackdidact/archive/v1.1.0.tar.gz
Keywords: stackoverflow terminal
Platform: UNKNOWN
Classifier: Development Status :: 3 - Alpha
Classifier: Intended Audience :: Developers
Classifier: Topic :: Software Development :: Build Tools
Classifier: License :: OSI Approved :: MIT License
Classifier: Programming Language :: Python :: 3
Classifier: Programming Language :: Python :: 3.3
Classifier: Programming Language :: Python :: 3.4
Classifier: Programming Language :: Python :: 3.5
Classifier: Programming Language :: Python :: 3.6
Requires-Dist: click
Requires-Dist: colorama
Requires-Dist: requests
